setup.py
devdoo/__init__.py
devdoo/actions.py
devdoo/broker.py
devdoo/brokers.py
devdoo/check.py
devdoo/config.py
devdoo/connection.py
devdoo/convert.py
devdoo/data_response.py
devdoo/database.py
devdoo/datafilter.py
devdoo/datarest.py
devdoo/devdoo_broker.py
devdoo/devdoo_database.py
devdoo/devdoo_service.py
devdoo/endpoint.py
devdoo/pack.py
devdoo/response.py
devdoo/service.py
devdoo/service_db.py
devdoo/services.py
devdoo/socket.py
devdoo/stack.py
devdoo/stacks.py
devdoo/status.py
devdoo/validate.py
devdoo/yml.py
devdoo/yaml/__init__.py
devdoo/yaml/composer.py
devdoo/yaml/constructor.py
devdoo/yaml/cyaml.py
devdoo/yaml/dumper.py
devdoo/yaml/emitter.py
devdoo/yaml/error.py
devdoo/yaml/events.py
devdoo/yaml/loader.py
devdoo/yaml/nodes.py
devdoo/yaml/parser.py
devdoo/yaml/reader.py
devdoo/yaml/representer.py
devdoo/yaml/resolver.py
devdoo/yaml/scanner.py
devdoo/yaml/serializer.py
devdoo/yaml/tokens.py
devdoo/yaml/__init__.py
devdoo/yaml/composer.py
devdoo/yaml/constructor.py
devdoo/yaml/cyaml.py
devdoo/yaml/dumper.py
devdoo/yaml/emitter.py
devdoo/yaml/error.py
devdoo/yaml/events.py
devdoo/yaml/loader.py
devdoo/yaml/nodes.py
devdoo/yaml/parser.py
devdoo/yaml/reader.py
devdoo/yaml/representer.py
devdoo/yaml/resolver.py
devdoo/yaml/scanner.py
devdoo/yaml/serializer.py
devdoo/yaml/tokens.py
packagetest109.egg-info/PKG-INFO
packagetest109.egg-info/SOURCES.txt
packagetest109.egg-info/dependency_links.txt
packagetest109.egg-info/not-zip-safe
packagetest109.egg-info/top_level.txt