Metadata-Version: 1.0
Name: packagetest109
Version: 0.109
Summary: DevDoo Microservices
Home-page: http://github.com/storborg/funniest
Author: Israel Agoeiro
Author-email: israelagoeiro@gmail.com
License: MIT
Platform: UNKNOWN
